{
    "api": {
        "baseUrl": "http://localhost:3000/api/v1",
        "firstname": "john",
        "lastname": "doe",
        "email": "johndoe@gmail.com",
        "password": "123",
        "gender": "male",
        "jobRole": "programmer",
        "department": "It",
        "address": "001",
        "token": "eyJhbGciOiJIUzI1NiIsInR5cCI6IkpXVCJ9.eyJ1c2VySWQiOjIsImlhdCI6MTU3Mjg5OTM2NiwiZXhwIjoxNTcyOTg1NzY2fQ.qE4xQP_kFmZboF40SbOGKRa7T_vRoeLOY7YKilgUnp0",
        "gifUrl": "image/gif",
        "gifTitle": "test gif",
        "articleTitle": "Test Article Title",
        "articleBody": "Test article",
        "editedArticleTitle": "Edited Test Article Title",
        "editedArticleBody": "Edited Test Article",
        "articleId": "1",
        "gifId": "1",
        "articleComment": "Test article comment",
        "gifComment": "Test gif comment"
    }
}